pydal_psycopg3/__about__.py
pydal_psycopg3/__init__.py
pydal_psycopg3/py.typed
pydal_psycopg3-0.1.1.dist-info/METADATA
pydal_psycopg3-0.1.1.dist-info/WHEEL
pydal_psycopg3-0.1.1.dist-info/RECORD
