Metadata-Version: 2.4
Name: pydal-psycopg3
Version: 0.1.1
Summary: Experimental psycopg3 driver for pydal
Author-email: Robin van der Noord <robinvandernoord@gmail.com>
Requires-Python: >=3.10
Requires-Dist: psycopg<4,>3
Requires-Dist: pydal>=20250629.2
Provides-Extra: dev
Requires-Dist: pytest; extra == 'dev'
Requires-Dist: pytest-cov; extra == 'dev'
Requires-Dist: testcontainers; extra == 'dev'
